twopilabs/utils/scpi/__init__.py
twopilabs/utils/scpi/scpi_device.py
twopilabs/utils/scpi/scpi_exceptions.py
twopilabs/utils/scpi/scpi_resource.py
twopilabs/utils/scpi/scpi_transport_base.py
twopilabs/utils/scpi/scpi_transport_serial.py
twopilabs/utils/scpi/scpi_transport_tcpip.py
twopilabs/utils/scpi/scpi_transport_usbcdc.py
twopilabs/utils/scpi/scpi_transport_usbtmc.py
twopilabs/utils/scpi/scpi_type_base.py
twopilabs/utils/scpi/scpi_types.py
twopilabs_utils_scpi-0.7.1.dist-info/licenses/LICENSE
twopilabs_utils_scpi-0.7.1.dist-info/METADATA
twopilabs_utils_scpi-0.7.1.dist-info/WHEEL
twopilabs_utils_scpi-0.7.1.dist-info/top_level.txt
twopilabs_utils_scpi-0.7.1.dist-info/RECORD
