Metadata-Version: 2.4
Name: twopilabs-utils-scpi
Version: 0.7.1
Summary: A SCPI command/parameter abstraction layer for interfacing with measurement equipment
Home-page: https://www.2pi-labs.com
Author: 2pi-Labs GmbH
Author-email: opensource@2pi-labs.com
License: LGPLv3
Classifier: License :: OSI Approved :: GNU Lesser General Public License v3 (LGPLv3)
Classifier: Programming Language :: Python :: 3
Requires-Python: >=3.6
License-File: LICENSE
Requires-Dist: pyserial
Requires-Dist: zeroconf>=0.33.0
Requires-Dist: wrapt
Requires-Dist: twopilabs-utils-usbtmc
Requires-Dist: twopilabs-utils-usbcdc
Dynamic: license-file
